forestatrisk/__init__.py
forestatrisk/hbm.cpython-310-darwin.so
forestatrisk/forestatrisk.py
forestatrisk/misc/__init__.py
forestatrisk/misc/countpix.py
forestatrisk/misc/miscellaneous.py
forestatrisk/validate/validation_udef_arp.py
forestatrisk/validate/map_validation.py
forestatrisk/validate/resample_sum.py
forestatrisk/validate/__init__.py
forestatrisk/validate/map_accuracy.py
forestatrisk/validate/model_validation.py
forestatrisk/validate/diffproj.py
forestatrisk/validate/validation_npix.py
forestatrisk/plot/plot.py
forestatrisk/plot/scalebar.py
forestatrisk/plot/niceplot.py
forestatrisk/plot/__init__.py
forestatrisk/shell/data_country.sh
forestatrisk/shell/forest_country.sh
forestatrisk/project/__init__.py
forestatrisk/project/deforest.py
forestatrisk/project/deforest_diffusion.py
forestatrisk/project/emissions.py
forestatrisk/project/allocate_deforestation.py
forestatrisk/predict/wrast_rho.py
forestatrisk/predict/interpolate_rho.py
forestatrisk/predict/predict_raster_binomial_iCAR.py
forestatrisk/predict/__init__.py
forestatrisk/predict/defrate_per_cat.py
forestatrisk/predict/predict_raster.py
forestatrisk/csv/ctry_run.csv
forestatrisk/csv/countrycode.csv
forestatrisk/model/model_binomial_iCAR.py
forestatrisk/model/__init__.py
forestatrisk/model/cellneigh.py
forestatrisk/model/icarModelPred.py
forestatrisk/model/model_random_forest.py
forestatrisk/data/get_vector_extent.py
forestatrisk/data/__init__.py
forestatrisk/data/create_symbolic_links.py
forestatrisk/data/country_download.py
forestatrisk/data/check_fcc.py
forestatrisk/data/country_compute.py
forestatrisk/data/check_aoi.py
forestatrisk/data/sample.py
forestatrisk/data/compute/mosaic_biomass_whrc.py
forestatrisk/data/compute/compute_biomass_whrc.py
forestatrisk/data/compute/compute_osm.py
forestatrisk/data/compute/compute_forest.py
forestatrisk/data/compute/compute_gadm.py
forestatrisk/data/compute/__init__.py
forestatrisk-1.3.2.dist-info/RECORD
forestatrisk-1.3.2.dist-info/LICENSE
forestatrisk-1.3.2.dist-info/WHEEL
forestatrisk-1.3.2.dist-info/entry_points.txt
forestatrisk-1.3.2.dist-info/top_level.txt
forestatrisk-1.3.2.dist-info/METADATA
