Metadata-Version: 2.2
Name: forestatrisk
Version: 1.3.2
Summary: Modelling and forecasting deforestation in the tropics
Home-page: https://github.com/ghislainv/forestatrisk
Author: Ghislain Vieilledent
Author-email: ghislain.vieilledent@cirad.fr
License: GPLv3
Keywords: deforestation hbm hierarchical logistic model probability risk Bayesian spatial autocorrelation
Classifier: Development Status :: 4 - Beta
Classifier: License :: OSI Approved :: GNU General Public License v3 (GPLv3)
Classifier: Programming Language :: Python :: 3
Classifier: Operating System :: OS Independent
Classifier: Topic :: Scientific/Engineering :: Bio-Informatics
Requires-Python: >=3.6
License-File: LICENSE
Requires-Dist: gdal
Requires-Dist: numpy
Requires-Dist: matplotlib
Requires-Dist: pandas
Requires-Dist: patsy
Requires-Dist: pywdpa
Requires-Dist: scikit-learn
Requires-Dist: geefcc
Provides-Extra: interactive
Requires-Dist: jupyter; extra == "interactive"
Requires-Dist: python-dotenv; extra == "interactive"
Requires-Dist: geopandas; extra == "interactive"
Requires-Dist: descartes; extra == "interactive"
Requires-Dist: folium; extra == "interactive"
Dynamic: author
Dynamic: author-email
Dynamic: classifier
Dynamic: description
Dynamic: description-content-type
Dynamic: home-page
Dynamic: keywords
Dynamic: license
Dynamic: provides-extra
Dynamic: requires-dist
Dynamic: requires-python
Dynamic: summary
